xaitk_saliency_demo/__init__.py
xaitk_saliency_demo/app/__init__.py
xaitk_saliency_demo/app/__main__.py
xaitk_saliency_demo/app/config.py
xaitk_saliency_demo/app/core.py
xaitk_saliency_demo/app/image.py
xaitk_saliency_demo/app/jupyter.py
xaitk_saliency_demo/app/main.py
xaitk_saliency_demo/app/xaitk_widgets.py
xaitk_saliency_demo/app/ml/__init__.py
xaitk_saliency_demo/app/ml/models.py
xaitk_saliency_demo/app/ml/xai.py
xaitk_saliency_demo/app/ml/assets/__init__.py
xaitk_saliency_demo/app/ml/assets/imagenet_classes.txt
xaitk_saliency_demo-2.6.0.dist-info/LICENSE
xaitk_saliency_demo-2.6.0.dist-info/METADATA
xaitk_saliency_demo-2.6.0.dist-info/WHEEL
xaitk_saliency_demo-2.6.0.dist-info/entry_points.txt
xaitk_saliency_demo-2.6.0.dist-info/top_level.txt
xaitk_saliency_demo-2.6.0.dist-info/RECORD
