Metadata-Version: 2.1
Name: xaitk-saliency-demo
Version: 2.6.0
Summary: Web application demonstrating XAITK Saliency functionality
Author: Kitware Inc.
License: BSD License
Keywords: Python,Interactive,Web,Application,Framework
Classifier: Development Status :: 5 - Production/Stable
Classifier: Environment :: Web Environment
Classifier: License :: OSI Approved :: BSD License
Classifier: Natural Language :: English
Classifier: Operating System :: OS Independent
Classifier: Programming Language :: Python :: 3 :: Only
Classifier: Programming Language :: JavaScript
Classifier: Topic :: Software Development :: Libraries :: Application Frameworks
Classifier: Topic :: Software Development :: Libraries :: Python Modules
License-File: LICENSE
Requires-Dist: trame>=3.2.7
Requires-Dist: trame-vuetify
Requires-Dist: trame-components>=2.2.1
Requires-Dist: trame-plotly>=3.0.2
Requires-Dist: plotly==5.15.0
Requires-Dist: pandas
Requires-Dist: smqtk-classifier==0.19.0
Requires-Dist: smqtk-core==0.19.0
Requires-Dist: smqtk-dataprovider==0.18.0
Requires-Dist: smqtk-descriptors==0.19.0
Requires-Dist: smqtk-detection[centernet,torch]==0.20.0
Requires-Dist: smqtk-image-io==0.17.1
Requires-Dist: xaitk-saliency==0.12.0
Requires-Dist: ubelt==1.3.2
Requires-Dist: torch!=2.0.1,>=1.9.0
Requires-Dist: torchvision>=0.10.0
Requires-Dist: transformers
Requires-Dist: scikit-learn==1.5.0
Requires-Dist: scikit-image==0.21.0
